wt_resource_tool/__init__.py
wt_resource_tool/_client.py
wt_resource_tool/py.typed
wt_resource_tool/parser/__init__.py
wt_resource_tool/parser/player_medal_parser.py
wt_resource_tool/parser/player_title_parser.py
wt_resource_tool/parser/tools.py
wt_resource_tool/parser/vehicle_data_parser.py
wt_resource_tool/schema/__init__.py
wt_resource_tool/schema/_common.py
wt_resource_tool/schema/_medal.py
wt_resource_tool/schema/_title.py
wt_resource_tool/schema/_vehicle.py
wt_resource_tool-0.5.0.dist-info/METADATA
wt_resource_tool-0.5.0.dist-info/WHEEL
wt_resource_tool-0.5.0.dist-info/licenses/LICENSE
wt_resource_tool-0.5.0.dist-info/RECORD
