Metadata-Version: 2.4
Name: wt-resource-tool
Version: 0.5.0
Author-email: axiangcoding <axiangcoding@gmail.com>
License-File: LICENSE
Requires-Python: <4.0,>=3.12
Requires-Dist: aiofiles<25.0.0,>=24.1.0
Requires-Dist: deprecated>=1.2.18
Requires-Dist: httpx<0.29.0,>=0.28.1
Requires-Dist: loguru<0.8.0,>=0.7.3
Requires-Dist: pandas<3.0.0,>=2.2.3
Requires-Dist: pydantic-settings<3.0.0,>=2.8.1
Requires-Dist: pydantic<3.0.0,>=2.10.6
Requires-Dist: python-dotenv<2.0.0,>=1.1.0
